pip_services4_commons/__init__.py
pip_services4_commons/convert/ArrayConverter.py
pip_services4_commons/convert/BooleanConverter.py
pip_services4_commons/convert/DateTimeConverter.py
pip_services4_commons/convert/DoubleConverter.py
pip_services4_commons/convert/FloatConverter.py
pip_services4_commons/convert/IntegerConverter.py
pip_services4_commons/convert/JsonConverter.py
pip_services4_commons/convert/LongConverter.py
pip_services4_commons/convert/MapConverter.py
pip_services4_commons/convert/RecursiveMapConverter.py
pip_services4_commons/convert/StringConverter.py
pip_services4_commons/convert/TypeCode.py
pip_services4_commons/convert/TypeConverter.py
pip_services4_commons/convert/UTC.py
pip_services4_commons/convert/__init__.py
pip_services4_commons/data/AnyValue.py
pip_services4_commons/data/AnyValueArray.py
pip_services4_commons/data/AnyValueMap.py
pip_services4_commons/data/ICloneable.py
pip_services4_commons/data/StringValueMap.py
pip_services4_commons/data/__init__.py
pip_services4_commons/errors/ApplicationException.py
pip_services4_commons/errors/ApplicationExceptionFactory.py
pip_services4_commons/errors/BadRequestException.py
pip_services4_commons/errors/ConfigException.py
pip_services4_commons/errors/ConflictException.py
pip_services4_commons/errors/ConnectionException.py
pip_services4_commons/errors/ErrorCategory.py
pip_services4_commons/errors/ErrorDescription.py
pip_services4_commons/errors/ErrorDescriptionFactory.py
pip_services4_commons/errors/FileException.py
pip_services4_commons/errors/InternalException.py
pip_services4_commons/errors/InvalidStateException.py
pip_services4_commons/errors/InvocationException.py
pip_services4_commons/errors/NotFoundException.py
pip_services4_commons/errors/UnauthorizedException.py
pip_services4_commons/errors/UnknownException.py
pip_services4_commons/errors/UnsupportedException.py
pip_services4_commons/errors/__init__.py
pip_services4_commons/reflect/MethodReflector.py
pip_services4_commons-0.0.2.dist-info/LICENSE
pip_services4_commons-0.0.2.dist-info/METADATA
pip_services4_commons-0.0.2.dist-info/WHEEL
pip_services4_commons-0.0.2.dist-info/top_level.txt
pip_services4_commons-0.0.2.dist-info/zip-safe
pip_services4_commons-0.0.2.dist-info/RECORD
